pyathenajdbc/AthenaJDBC42.jar
pyathenajdbc/__init__.py
pyathenajdbc/connection.py
pyathenajdbc/converter.py
pyathenajdbc/cursor.py
pyathenajdbc/error.py
pyathenajdbc/formatter.py
pyathenajdbc/log4j.properties
pyathenajdbc/py.typed
pyathenajdbc/sqlalchemy_athena.py
pyathenajdbc/util.py
pyathenajdbc-3.0.0.dist-info/entry_points.txt
pyathenajdbc-3.0.0.dist-info/LICENSE
pyathenajdbc-3.0.0.dist-info/WHEEL
pyathenajdbc-3.0.0.dist-info/METADATA
pyathenajdbc-3.0.0.dist-info/RECORD
