Metadata-Version: 2.1
Name: pyathenajdbc
Version: 3.0.0
Summary: Amazon Athena JDBC driver wrapper for the Python DB API 2.0 (PEP 249)
Home-page: https://github.com/laughingman7743/PyAthenaJDBC/
License: MIT
Author: laughingman7743
Author-email: laughingman7743@gmail.com
Requires-Python: >=3.6.1,<4.0.0
Classifier: Development Status :: 4 - Beta
Classifier: Intended Audience :: Developers
Classifier: License :: OSI Approved :: MIT License
Classifier: Operating System :: OS Independent
Classifier: Programming Language :: Java
Classifier: Programming Language :: Python :: 3
Classifier: Programming Language :: Python :: 3.6
Classifier: Programming Language :: Python :: 3.7
Classifier: Programming Language :: Python :: 3.8
Classifier: Programming Language :: Python :: 3.9
Classifier: Topic :: Database :: Front-Ends
Provides-Extra: pandas
Provides-Extra: sqlalchemy
Requires-Dist: jpype1 (>=1.1.0,<2.0.0)
Requires-Dist: pandas (>=1.0.0); extra == "pandas"
Requires-Dist: sqlalchemy (>=1.0.0,<2.0.0); extra == "sqlalchemy"
